#pragma once

void (*print_vet[256]);
void set_print_vet(){
  print_vet[0] = print_jvm_nop;
  print_vet[1] = print_jvm_aconst_null;
  print_vet[2] = print_jvm_iconst_m1;
  print_vet[3] = print_jvm_iconst_0;
  print_vet[4] = print_jvm_iconst_1;
  print_vet[5] = print_jvm_iconst_2;
  print_vet[6] = print_jvm_iconst_3;
  print_vet[7] = print_jvm_iconst_4;
  print_vet[8] = print_jvm_iconst_5;
  print_vet[9] = print_jvm_lconst_0;
  print_vet[10] = print_jvm_lconst_1;
  print_vet[11] = print_jvm_fconst_0;
  print_vet[12] = print_jvm_fconst_1;
  print_vet[13] = print_jvm_fconst_2;
  print_vet[14] = print_jvm_dconst_0;
  print_vet[15] = print_jvm_dconst_1;
  print_vet[16] = print_jvm_bipush;
  print_vet[17] = print_jvm_sipush;
  print_vet[18] = print_jvm_ldc;
  print_vet[19] = print_jvm_ldc_w;
  print_vet[20] = print_jvm_ldc2_w;
  print_vet[21] = print_jvm_iload;
  print_vet[22] = print_jvm_lload;
  print_vet[23] = print_jvm_fload;
  print_vet[24] = print_jvm_dload;
  print_vet[25] = print_jvm_aload;
  print_vet[26] = print_jvm_iload_0;
  print_vet[27] = print_jvm_iload_1;
  print_vet[28] = print_jvm_iload_2;
  print_vet[29] = print_jvm_iload_3;
  print_vet[30] = print_jvm_lload_0;
  print_vet[31] = print_jvm_lload_1;
  print_vet[32] = print_jvm_lload_2;
  print_vet[33] = print_jvm_lload_3;
  print_vet[34] = print_jvm_fload_0;
  print_vet[35] = print_jvm_fload_1;
  print_vet[36] = print_jvm_fload_2;
  print_vet[37] = print_jvm_fload_3;
  print_vet[38] = print_jvm_dload_0;
  print_vet[39] = print_jvm_dload_1;
  print_vet[40] = print_jvm_dload_2;
  print_vet[41] = print_jvm_dload_3;
  print_vet[42] = print_jvm_aload_0;
  print_vet[43] = print_jvm_aload_1;
  print_vet[44] = print_jvm_aload_2;
  print_vet[45] = print_jvm_aload_3;
  print_vet[46] = print_jvm_iaload;
  print_vet[47] = print_jvm_faload;
  print_vet[48] = print_jvm_daload;
  print_vet[49] = print_jvm_aaload;
  print_vet[50] = print_jvm_baload;
  print_vet[51] = print_jvm_caload;
  print_vet[52] = print_jvm_saload;
  print_vet[54] = print_jvm_istore;
  print_vet[55] = print_jvm_lstore;
  print_vet[56] = print_jvm_fstore;
  print_vet[57] = print_jvm_dstore;
  print_vet[58] = print_jvm_astore;
  print_vet[59] = print_jvm_istore_0;
  print_vet[60] = print_jvm_istore_1;
  print_vet[61] = print_jvm_istore_2;
  print_vet[62] = print_jvm_istore_3;
  print_vet[63] = print_jvm_lstore_0;
  print_vet[64] = print_jvm_lstore_1;
  print_vet[65] = print_jvm_lstore_2;
  print_vet[66] = print_jvm_lstore_3;
  print_vet[67] = print_jvm_fstore_0;
  print_vet[68] = print_jvm_fstore_1;
  print_vet[69] = print_jvm_fstore_2;
  print_vet[70] = print_jvm_fstore_3;
  print_vet[71] = print_jvm_dstore_0;
  print_vet[72] = print_jvm_dstore_1;
  print_vet[73] = print_jvm_dstore_2;
  print_vet[74] = print_jvm_dstore_3;
  print_vet[75] = print_jvm_astore_0;
  print_vet[76] = print_jvm_astore_1;
  print_vet[77] = print_jvm_astore_2;
  print_vet[78] = print_jvm_astore_3;
  print_vet[79] = print_jvm_iastore;
  print_vet[80] = print_jvm_lastore;
  print_vet[81] = print_jvm_fastore;
  print_vet[82] = print_jvm_dastore;
  print_vet[83] = print_jvm_aastore;
  print_vet[84] = print_jvm_bastore;
  print_vet[85] = print_jvm_castore;
  print_vet[86] = print_jvm_sastore;
  print_vet[87] = print_jvm_pop;
  print_vet[88] = print_jvm_pop2;
  print_vet[89] = print_jvm_dup;
  print_vet[90] = print_jvm_dup_x1;
  print_vet[91] = print_jvm_dup_x2;
  print_vet[92] = print_jvm_dup2;
  print_vet[93] = print_jvm_dup2_x1;
  print_vet[94] = print_jvm_dup2_x2;
  print_vet[95] = print_jvm_swap;
  print_vet[96] = print_jvm_iadd;
  print_vet[97] = print_jvm_ladd;
  print_vet[98] = print_jvm_fadd;
  print_vet[99] = print_jvm_dadd;
  print_vet[100] = print_jvm_isub;
  print_vet[101] = print_jvm_lsub;
  print_vet[102] = print_jvm_fsub;
  print_vet[103] = print_jvm_dsub;
  print_vet[104] = print_jvm_imul;
  print_vet[105] = print_jvm_lmul;
  print_vet[106] = print_jvm_fmul;
  print_vet[107] = print_jvm_dmul;
  print_vet[108] = print_jvm_idiv;
  print_vet[109] = print_jvm_ldiv;
  print_vet[110] = print_jvm_fdiv;
  print_vet[111] = print_jvm_ddiv;
  print_vet[112] = print_jvm_irem;
  print_vet[113] = print_jvm_lrem;
  print_vet[114] = print_jvm_frem;
  print_vet[115] = print_jvm_drem;
  print_vet[116] = print_jvm_ineg;
  print_vet[117] = print_jvm_lneg;
  print_vet[118] = print_jvm_fneg;
  print_vet[119] = print_jvm_dneg;
  print_vet[120] = print_jvm_ishl;
  print_vet[121] = print_jvm_lshl;
  print_vet[122] = print_jvm_ishr;
  print_vet[123] = print_jvm_lshr;
  print_vet[124] = print_jvm_iushr;
  print_vet[125] = print_jvm_lushr;
  print_vet[126] = print_jvm_iand;
  print_vet[127] = print_jvm_land;
  print_vet[128] = print_jvm_ior;
  print_vet[129] = print_jvm_lor;
  print_vet[130] = print_jvm_ixor;
  print_vet[131] = print_jvm_lxor;
  print_vet[132] = print_jvm_iinc;
  print_vet[133] = print_jvm_i2l;
  print_vet[134] = print_jvm_i2f;
  print_vet[135] = print_jvm_i2d;
  print_vet[136] = print_jvm_l2i;
  print_vet[137] = print_jvm_l2f;
  print_vet[138] = print_jvm_l2d;
  print_vet[139] = print_jvm_f2i;
  print_vet[140] = print_jvm_f2l;
  print_vet[141] = print_jvm_f2d;
  print_vet[142] = print_jvm_d2i;
  print_vet[143] = print_jvm_d2l;
  print_vet[144] = print_jvm_d2f;
  print_vet[145] = print_jvm_i2b;
  print_vet[146] = print_jvm_i2c;
  print_vet[147] = print_jvm_i2s;
  print_vet[148] = print_jvm_lcmp;
  print_vet[149] = print_jvm_fcmpl;
  print_vet[150] = print_jvm_fcmpg;
  print_vet[151] = print_jvm_dcmpl;
  print_vet[152] = print_jvm_dcmpg;
  print_vet[153] = print_jvm_ifeq;
  print_vet[154] = print_jvm_ifne;
  print_vet[155] = print_jvm_iflt;
  print_vet[156] = print_jvm_ifge;
  print_vet[157] = print_jvm_ifgt;
  print_vet[158] = print_jvm_ifle;
  print_vet[159] = print_jvm_if_icmpeq;
  print_vet[160] = print_jvm_if_icmpne;
  print_vet[161] = print_jvm_if_icmplt;
  print_vet[162] = print_jvm_if_icmpge;
  print_vet[163] = print_jvm_if_icmpgt;
  print_vet[164] = print_jvm_if_icmple;
  print_vet[165] = print_jvm_if_acmpeq;
  print_vet[166] = print_jvm_if_acmpne;
  print_vet[167] = print_jvm_goto;
  print_vet[168] = print_jvm_jsr;
  print_vet[169] = print_jvm_ret;
  print_vet[170] = print_jvm_tableswitch;
  print_vet[171] = print_jvm_lookupswitch;
  print_vet[172] = print_jvm_ireturn;
  print_vet[173] = print_jvm_lreturn;
  print_vet[174] = print_jvm_freturn;
  print_vet[175] = print_jvm_dreturn;
  print_vet[176] = print_jvm_areturn;
  print_vet[177] = print_jvm_return;
  print_vet[178] = print_jvm_getstatic;
  print_vet[179] = print_jvm_putstatic;
  print_vet[180] = print_jvm_getfield;
  print_vet[181] = print_jvm_putfield;
  print_vet[182] = print_jvm_invokevirtual;
  print_vet[183] = print_jvm_invokespecial;
  print_vet[184] = print_jvm_invokestatic;
  print_vet[185] = print_jvm_invokeinterface;
  print_vet[186] = print_jvm_invokedynamic;
  print_vet[187] = print_jvm_new;
  print_vet[188] = print_jvm_newarray;
  print_vet[189] = print_jvm_anewarray;
  print_vet[190] = print_jvm_arraylength;
  print_vet[191] = print_jvm_athrow;
  print_vet[192] = print_jvm_checkcast;
  print_vet[193] = print_jvm_instanceof;
  print_vet[194] = print_jvm_monitorenter;
  print_vet[195] = print_jvm_monitorexit;
  print_vet[196] = print_jvm_wide;
  print_vet[197] = print_jvm_multianewarray;
  print_vet[198] = print_jvm_ifnull;
  print_vet[199] = print_jvm_ifnonnull;
  print_vet[200] = print_jvm_goto_w;
  print_vet[201] = print_jvm_jsr_w;
  print_vet[202] = print_jvm_breakpoint;
  print_vet[254] = print_jvm_impdep1;
  print_vet[255] = print_jvm_impdep2;
  return;
}
